{
  "pattern": {
    "panels": {
      "left_sleeve_f": {
        "translation": [
          32.56130340453335,
          127.75849414339746,
          17.5
        ],
        "rotation": [
          0.0,
          0.0,
          -45.482999999999976
        ],
        "vertices": [
          [
            0.0,
            0.0
          ],
          [
            -20.605424419115923,
            0.0
          ],
          [
            -6.527863019795035,
            -15.641954745282588
          ],
          [
            0.0,
            -24.66041869591985
          ]
        ],
        "edges": [
          {
            "endpoints": [
              0,
              1
            ]
          },
          {
            "endpoints": [
              1,
              2
            ],
            "curvature": {
              "type": "cubic",
              "params": [
                [
                  0.338793861678933,
                  -0.2889591171996692
                ],
                [
                  0.6722611607994566,
                  0.04613647842505868
                ]
              ]
            }
          },
          {
            "endpoints": [
              2,
              3
            ]
          },
          {
            "endpoints": [
              3,
              0
            ]
          }
        ],
        "label": "arm"
      },
      "left_sleeve_b": {
        "translation": [
          32.56130340453335,
          127.75849414339746,
          -12.5
        ],
        "rotation": [
          0.0,
          0.0,
          -45.482999999999976
        ],
        "vertices": [
          [
            0.0,
            0.0
          ],
          [
            0.0,
            -24.660418695919965
          ],
          [
            -6.527863019795035,
            -15.64195474528266
          ],
          [
            -20.609820638120667,
            -0.25833316847366206
          ],
          [
            -20.60542441911592,
            0.0
          ]
        ],
        "edges": [
          {
            "endpoints": [
              0,
              1
            ]
          },
          {
            "endpoints": [
              1,
              2
            ]
          },
          {
            "endpoints": [
              2,
              3
            ],
            "curvature": {
              "type": "cubic",
              "params": [
                [
                  0.334963227764279,
                  -0.04489726099923504
                ],
                [
                  0.6370902323175487,
                  0.31492698152623955
                ]
              ]
            }
          },
          {
            "endpoints": [
              3,
              4
            ],
            "curvature": {
              "type": "cubic",
              "params": [
                [
                  0.3361580748243874,
                  0.0031932457185116407
                ],
                [
                  0.6694778564417578,
                  0.003177650185466161
                ]
              ]
            }
          },
          {
            "endpoints": [
              4,
              0
            ]
          }
        ],
        "label": "arm"
      },
      "sl_left_cuff_skirt_b": {
        "translation": [
          70.81917247826598,
          110.17979852839633,
          -12.5
        ],
        "rotation": [
          0.0,
          0.0,
          44.517000000000024
        ],
        "vertices": [
          [
            0.0,
            0.0
          ],
          [
            -47.17625768375392,
            0.0
          ],
          [
            -32.88833758506388,
            25.450390819507646
          ],
          [
            -14.28792009869004,
            25.450390819507646
          ]
        ],
        "edges": [
          {
            "endpoints": [
              0,
              1
            ]
          },
          {
            "endpoints": [
              1,
              2
            ]
          },
          {
            "endpoints": [
              2,
              3
            ]
          },
          {
            "endpoints": [
              3,
              0
            ]
          }
        ],
        "label": "arm"
      },
      "sl_left_cuff_skirt_f": {
        "translation": [
          70.81917247826598,
          110.17979852839633,
          17.5
        ],
        "rotation": [
          0.0,
          0.0,
          44.517000000000024
        ],
        "vertices": [
          [
            0.0,
            0.0
          ],
          [
            -14.28792009869004,
            25.450390819507646
          ],
          [
            -32.88833758506388,
            25.450390819507646
          ],
          [
            -47.17625768375392,
            0.0
          ]
        ],
        "edges": [
          {
            "endpoints": [
              0,
              1
            ]
          },
          {
            "endpoints": [
              1,
              2
            ]
          },
          {
            "endpoints": [
              2,
              3
            ]
          },
          {
            "endpoints": [
              3,
              0
            ]
          }
        ],
        "label": "arm"
      },
      "sl_left_cuff_b": {
        "translation": [
          40.90979870084271,
          119.2680441814295,
          -12.5
        ],
        "rotation": [
          0.0,
          0.0,
          44.517000000000024
        ],
        "vertices": [
          [
            0.0,
            0.0
          ],
          [
            -17.266868344365413,
            0.0
          ],
          [
            -17.266868344365413,
            9.90735546917036
          ],
          [
            0.0,
            9.90735546917036
          ]
        ],
        "edges": [
          {
            "endpoints": [
              0,
              1
            ]
          },
          {
            "endpoints": [
              1,
              2
            ]
          },
          {
            "endpoints": [
              2,
              3
            ]
          },
          {
            "endpoints": [
              3,
              0
            ]
          }
        ],
        "label": "arm"
      },
      "sl_left_cuff_f": {
        "translation": [
          40.90979870084271,
          119.2680441814295,
          17.5
        ],
        "rotation": [
          0.0,
          0.0,
          44.517000000000024
        ],
        "vertices": [
          [
            0.0,
            0.0
          ],
          [
            0.0,
            9.90735546917036
          ],
          [
            -17.266868344365413,
            9.90735546917036
          ],
          [
            -17.266868344365413,
            0.0
          ]
        ],
        "edges": [
          {
            "endpoints": [
              0,
              1
            ]
          },
          {
            "endpoints": [
              1,
              2
            ]
          },
          {
            "endpoints": [
              2,
              3
            ]
          },
          {
            "endpoints": [
              3,
              0
            ]
          }
        ],
        "label": "arm"
      },
      "left_btorso": {
        "translation": [
          0.0,
          103.895647186128,
          -25.0
        ],
        "rotation": [
          0.0,
          0.0,
          0.0
        ],
        "vertices": [
          [
            0.0,
            0.36889166233942916
          ],
          [
            0.0,
            32.661477908945876
          ],
          [
            14.113865742474928,
            32.661477908945876
          ],
          [
            14.628361652835284,
            36.322306531814455
          ],
          [
            17.2284,
            35.28879738065446
          ],
          [
            23.83805,
            16.847317380654456
          ],
          [
            23.83805,
            12.233866666666664
          ],
          [
            23.126358333333332,
            -2.0
          ],
          [
            14.916717524757459,
            -0.5550002787946218
          ],
          [
            15.282781625402311,
            10.242436235405265
          ],
          [
            13.149513068956622,
            -0.3484940103303784
          ],
          [
            8.60976632837318,
            0.061960367182088305
          ],
          [
            8.486933461521588,
            12.06537639301566
          ],
          [
            6.834173497888344,
            0.175655256461269
          ]
        ],
        "edges": [
          {
            "endpoints": [
              0,
              1
            ]
          },
          {
            "endpoints": [
              1,
              2
            ],
            "label": "left_collar"
          },
          {
            "endpoints": [
              2,
              3
            ],
            "label": "left_collar"
          },
          {
            "endpoints": [
              3,
              4
            ]
          },
          {
            "endpoints": [
              4,
              5
            ],
            "label": "left_armhole",
            "curvature": {
              "type": "cubic",
              "params": [
                [
                  0.5,
                  -0.2
                ],
                [
                  0.8,
                  -0.35
                ]
              ]
            }
          },
          {
            "endpoints": [
              5,
              6
            ]
          },
          {
            "endpoints": [
              6,
              7
            ]
          },
          {
            "endpoints": [
              7,
              8
            ],
            "curvature": {
              "type": "quadratic",
              "params": [
                [
                  0.5019803766939228,
                  -0.01839842016264157
                ]
              ]
            }
          },
          {
            "endpoints": [
              8,
              9
            ]
          },
          {
            "endpoints": [
              9,
              10
            ]
          },
          {
            "endpoints": [
              10,
              11
            ],
            "curvature": {
              "type": "quadratic",
              "params": [
                [
                  0.5003470519620727,
                  -0.00942210554185744
                ]
              ]
            }
          },
          {
            "endpoints": [
              11,
              12
            ]
          },
          {
            "endpoints": [
              12,
              13
            ]
          },
          {
            "endpoints": [
              13,
              0
            ],
            "curvature": {
              "type": "quadratic",
              "params": [
                [
                  0.49964505281690064,
                  -0.014147551785365786
                ]
              ]
            }
          }
        ],
        "label": "body"
      },
      "left_ftorso": {
        "translation": [
          0.0,
          97.85775552378857,
          30.0
        ],
        "rotation": [
          0.0,
          0.0,
          0.0
        ],
        "vertices": [
          [
            0.0,
            0.0
          ],
          [
            8.473150131373654,
            0.0
          ],
          [
            9.634250131373655,
            12.757752334184888
          ],
          [
            10.795350131373658,
            2.8438747969799893e-16
          ],
          [
            24.921200000000002,
            0.0
          ],
          [
            26.082300000000004,
            14.233866642059992
          ],
          [
            13.003468750843743,
            16.06836664205999
          ],
          [
            26.082300000000004,
            17.90286664205999
          ],
          [
            24.46108877526564,
            22.579840538285193
          ],
          [
            17.0686818644478,
            40.76295828759291
          ],
          [
            17.068593319850624,
            41.021320538285195
          ],
          [
            14.628361652835281,
            41.99130646823674
          ],
          [
            0.0,
            27.362944815367158
          ]
        ],
        "edges": [
          {
            "endpoints": [
              0,
              1
            ]
          },
          {
            "endpoints": [
              1,
              2
            ]
          },
          {
            "endpoints": [
              2,
              3
            ]
          },
          {
            "endpoints": [
              3,
              4
            ]
          },
          {
            "endpoints": [
              4,
              5
            ]
          },
          {
            "endpoints": [
              5,
              6
            ]
          },
          {
            "endpoints": [
              6,
              7
            ]
          },
          {
            "endpoints": [
              7,
              8
            ]
          },
          {
            "endpoints": [
              8,
              9
            ],
            "curvature": {
              "type": "cubic",
              "params": [
                [
                  0.20252414672385655,
                  0.3504253330434686
                ],
                [
                  0.5022031868138364,
                  0.20240518174169267
                ]
              ]
            }
          },
          {
            "endpoints": [
              9,
              10
            ],
            "curvature": {
              "type": "cubic",
              "params": [
                [
                  0.33230739189901215,
                  -0.00012776941168113394
                ],
                [
                  0.6656417298323608,
                  -0.00013390712863602984
                ]
              ]
            }
          },
          {
            "endpoints": [
              10,
              11
            ]
          },
          {
            "endpoints": [
              11,
              12
            ],
            "label": "left_collar",
            "curvature": {
              "type": "circle",
              "params": [
                14.628361652852453,
                0,
                0
              ]
            }
          },
          {
            "endpoints": [
              12,
              0
            ]
          }
        ],
        "label": "body"
      },
      "right_btorso": {
        "translation": [
          0.0,
          103.895647186128,
          -25.0
        ],
        "rotation": [
          0.0,
          0.0,
          0.0
        ],
        "vertices": [
          [
            0,
            0.36889166233942916
          ],
          [
            -6.834173497888344,
            0.175655256461269
          ],
          [
            -8.486933461521588,
            12.06537639301566
          ],
          [
            -8.60976632837318,
            0.061960367182088305
          ],
          [
            -13.149513068956622,
            -0.3484940103303784
          ],
          [
            -15.282781625402311,
            10.242436235405265
          ],
          [
            -14.916717524757459,
            -0.5550002787946218
          ],
          [
            -23.126358333333332,
            -2
          ],
          [
            -23.83805,
            12.233866666666664
          ],
          [
            -23.83805,
            16.847317380654456
          ],
          [
            -17.2284,
            35.28879738065446
          ],
          [
            -10.6231167981982,
            37.91438162018973
          ],
          [
            0.0,
            32.66147795061595
          ]
        ],
        "edges": [
          {
            "endpoints": [
              0,
              1
            ],
            "curvature": {
              "type": "quadratic",
              "params": [
                [
                  0.5003549471830994,
                  -0.014147551785365786
                ]
              ]
            }
          },
          {
            "endpoints": [
              1,
              2
            ]
          },
          {
            "endpoints": [
              2,
              3
            ]
          },
          {
            "endpoints": [
              3,
              4
            ],
            "curvature": {
              "type": "quadratic",
              "params": [
                [
                  0.4996529480379273,
                  -0.00942210554185744
                ]
              ]
            }
          },
          {
            "endpoints": [
              4,
              5
            ]
          },
          {
            "endpoints": [
              5,
              6
            ]
          },
          {
            "endpoints": [
              6,
              7
            ],
            "curvature": {
              "type": "quadratic",
              "params": [
                [
                  0.49801962330607724,
                  -0.01839842016264157
                ]
              ]
            }
          },
          {
            "endpoints": [
              7,
              8
            ]
          },
          {
            "endpoints": [
              8,
              9
            ]
          },
          {
            "endpoints": [
              9,
              10
            ],
            "label": "right_armhole",
            "curvature": {
              "type": "cubic",
              "params": [
                [
                  0.19999999999999996,
                  -0.35
                ],
                [
                  0.5,
                  -0.2
                ]
              ]
            }
          },
          {
            "endpoints": [
              10,
              11
            ]
          },
          {
            "endpoints": [
              11,
              12
            ],
            "label": "right_collar",
            "curvature": {
              "type": "circle",
              "params": [
                13.368187987481104,
                0,
                1
              ]
            }
          },
          {
            "endpoints": [
              12,
              0
            ]
          }
        ],
        "label": "body"
      },
      "right_ftorso": {
        "translation": [
          0.0,
          97.85775552378857,
          30.0
        ],
        "rotation": [
          0.0,
          0.0,
          0.0
        ],
        "vertices": [
          [
            0,
            0
          ],
          [
            0.0,
            27.39335622887448
          ],
          [
            -10.623116798198195,
            43.58338138535707
          ],
          [
            -17.068593319850624,
            41.021320538285195
          ],
          [
            -24.46108877526564,
            22.579840538285193
          ],
          [
            -26.082300000000004,
            17.90286664205999
          ],
          [
            -13.003468750843743,
            16.06836664205999
          ],
          [
            -26.082300000000004,
            14.233866642059992
          ],
          [
            -24.921200000000002,
            0
          ],
          [
            -10.795350131373658,
            2.8438747969799893e-16
          ],
          [
            -9.634250131373655,
            12.757752334184888
          ],
          [
            -8.473150131373654,
            0.0
          ]
        ],
        "edges": [
          {
            "endpoints": [
              0,
              1
            ]
          },
          {
            "endpoints": [
              1,
              2
            ],
            "label": "right_collar",
            "curvature": {
              "type": "circle",
              "params": [
                11.580202051927028,
                0,
                0
              ]
            }
          },
          {
            "endpoints": [
              2,
              3
            ]
          },
          {
            "endpoints": [
              3,
              4
            ],
            "label": "right_armhole",
            "curvature": {
              "type": "cubic",
              "params": [
                [
                  0.5,
                  0.2
                ],
                [
                  0.8,
                  0.35
                ]
              ]
            }
          },
          {
            "endpoints": [
              4,
              5
            ]
          },
          {
            "endpoints": [
              5,
              6
            ]
          },
          {
            "endpoints": [
              6,
              7
            ]
          },
          {
            "endpoints": [
              7,
              8
            ]
          },
          {
            "endpoints": [
              8,
              9
            ]
          },
          {
            "endpoints": [
              9,
              10
            ]
          },
          {
            "endpoints": [
              10,
              11
            ]
          },
          {
            "endpoints": [
              11,
              0
            ]
          }
        ],
        "label": "body"
      },
      "skirt_front": {
        "translation": [
          -29.780451662117432,
          61.650631010812276,
          25.0
        ],
        "rotation": [
          0.0,
          0.0,
          0.0
        ],
        "vertices": [
          [
            -0.36860166211743106,
            0.0
          ],
          [
            59.02290166211742,
            0.0
          ],
          [
            53.65429999999999,
            10.655277844146013
          ],
          [
            51.92614999999999,
            34.13897784414601
          ],
          [
            37.67833138050339,
            34.13897784414601
          ],
          [
            29.238441243468408,
            34.13897784414601
          ],
          [
            20.79855110643343,
            34.13897784414601
          ],
          [
            6.728149999999999,
            34.13897784414601
          ],
          [
            5,
            10.655277844146013
          ]
        ],
        "edges": [
          {
            "endpoints": [
              0,
              1
            ]
          },
          {
            "endpoints": [
              1,
              2
            ],
            "curvature": {
              "type": "quadratic",
              "params": [
                [
                  0.4939044269703794,
                  0.2549950741381537
                ]
              ]
            }
          },
          {
            "endpoints": [
              2,
              3
            ],
            "curvature": {
              "type": "quadratic",
              "params": [
                [
                  0.4985545385734096,
                  -0.03668751570317946
                ]
              ]
            }
          },
          {
            "endpoints": [
              3,
              4
            ],
            "label": "lower_interface"
          },
          {
            "endpoints": [
              4,
              5
            ],
            "label": "lower_interface"
          },
          {
            "endpoints": [
              5,
              6
            ],
            "label": "lower_interface"
          },
          {
            "endpoints": [
              6,
              7
            ],
            "label": "lower_interface"
          },
          {
            "endpoints": [
              7,
              8
            ],
            "curvature": {
              "type": "quadratic",
              "params": [
                [
                  0.5014454625191118,
                  -0.03668751567083784
                ]
              ]
            }
          },
          {
            "endpoints": [
              8,
              0
            ],
            "curvature": {
              "type": "quadratic",
              "params": [
                [
                  0.5060956073463587,
                  0.2549950888478611
                ]
              ]
            }
          }
        ],
        "label": "leg"
      },
      "skirt_back": {
        "translation": [
          -32.780451662117436,
          60.650631010812276,
          -20.0
        ],
        "rotation": [
          0.0,
          0.0,
          0.0
        ],
        "vertices": [
          [
            -0.3686016621174346,
            0.0
          ],
          [
            5,
            10.655277844146013
          ],
          [
            7.127992822930928,
            35.313162844146014
          ],
          [
            15.299518077285981,
            35.313162844146014
          ],
          [
            16.72850737155325,
            16.34511732790796
          ],
          [
            18.157496665820517,
            35.313162844146014
          ],
          [
            22.716046605358557,
            35.313162844146014
          ],
          [
            24.145035899625825,
            14.226196163142092
          ],
          [
            25.574025193893092,
            35.313162844146014
          ],
          [
            32.50055875653159,
            35.313162844146014
          ],
          [
            39.24967517337137,
            35.313162844146014
          ],
          [
            40.67866446763864,
            14.226196163142092
          ],
          [
            42.10765376190591,
            35.313162844146014
          ],
          [
            46.66620363029078,
            35.313162844146014
          ],
          [
            48.09519292455805,
            16.34511732790796
          ],
          [
            49.52418221882532,
            35.313162844146014
          ],
          [
            57.695707177069075,
            35.313162844146014
          ],
          [
            59.8237,
            10.655277844146013
          ],
          [
            65.19230166211744,
            0.0
          ]
        ],
        "edges": [
          {
            "endpoints": [
              0,
              1
            ],
            "curvature": {
              "type": "quadratic",
              "params": [
                [
                  0.4939043911171755,
                  -0.254995089622494
                ]
              ]
            }
          },
          {
            "endpoints": [
              1,
              2
            ],
            "curvature": {
              "type": "quadratic",
              "params": [
                [
                  0.49804539625805627,
                  0.042981660134458914
                ]
              ]
            }
          },
          {
            "endpoints": [
              2,
              3
            ],
            "label": "lower_interface"
          },
          {
            "endpoints": [
              3,
              4
            ]
          },
          {
            "endpoints": [
              4,
              5
            ]
          },
          {
            "endpoints": [
              5,
              6
            ],
            "label": "lower_interface"
          },
          {
            "endpoints": [
              6,
              7
            ]
          },
          {
            "endpoints": [
              7,
              8
            ]
          },
          {
            "endpoints": [
              8,
              9
            ],
            "label": "lower_interface"
          },
          {
            "endpoints": [
              9,
              10
            ],
            "label": "lower_interface"
          },
          {
            "endpoints": [
              10,
              11
            ]
          },
          {
            "endpoints": [
              11,
              12
            ]
          },
          {
            "endpoints": [
              12,
              13
            ],
            "label": "lower_interface"
          },
          {
            "endpoints": [
              13,
              14
            ]
          },
          {
            "endpoints": [
              14,
              15
            ]
          },
          {
            "endpoints": [
              15,
              16
            ],
            "label": "lower_interface"
          },
          {
            "endpoints": [
              16,
              17
            ],
            "curvature": {
              "type": "quadratic",
              "params": [
                [
                  0.5019546014275647,
                  0.04298166025769451
                ]
              ]
            }
          },
          {
            "endpoints": [
              17,
              18
            ],
            "curvature": {
              "type": "quadratic",
              "params": [
                [
                  0.5060955730755671,
                  -0.25499507416105954
                ]
              ]
            }
          },
          {
            "endpoints": [
              18,
              0
            ]
          }
        ],
        "label": "leg"
      },
      "skirt_front_0": {
        "translation": [
          -40.797122294235905,
          49.62939188713868,
          25.0
        ],
        "rotation": [
          0.0,
          0.0,
          0.0
        ],
        "vertices": [
          [
            0,
            0
          ],
          [
            81.84825142037894,
            0
          ],
          [
            77.84825142037894,
            6.521239123673589
          ],
          [
            4.0,
            6.521239123673589
          ]
        ],
        "edges": [
          {
            "endpoints": [
              0,
              1
            ]
          },
          {
            "endpoints": [
              1,
              2
            ]
          },
          {
            "endpoints": [
              2,
              3
            ]
          },
          {
            "endpoints": [
              3,
              0
            ]
          }
        ],
        "label": "leg"
      },
      "skirt_back_0": {
        "translation": [
          -44.797122294235905,
          49.62939188713868,
          -20.0
        ],
        "rotation": [
          0.0,
          0.0,
          0.0
        ],
        "vertices": [
          [
            0,
            0
          ],
          [
            4.0,
            6.521239123673589
          ],
          [
            85.59424458847181,
            6.521239123673589
          ],
          [
            89.59424458847181,
            0
          ]
        ],
        "edges": [
          {
            "endpoints": [
              0,
              1
            ]
          },
          {
            "endpoints": [
              1,
              2
            ]
          },
          {
            "endpoints": [
              2,
              3
            ]
          },
          {
            "endpoints": [
              3,
              0
            ]
          }
        ],
        "label": "leg"
      },
      "skirt_back_2": {
        "translation": [
          -76.04967760282253,
          26.58691363979149,
          -20.0
        ],
        "rotation": [
          0.0,
          0.0,
          0.0
        ],
        "vertices": [
          [
            0,
            0
          ],
          [
            4.0,
            6.521239123673589
          ],
          [
            148.09935520564505,
            6.521239123673589
          ],
          [
            152.09935520564505,
            0
          ]
        ],
        "edges": [
          {
            "endpoints": [
              0,
              1
            ]
          },
          {
            "endpoints": [
              1,
              2
            ]
          },
          {
            "endpoints": [
              2,
              3
            ]
          },
          {
            "endpoints": [
              3,
              0
            ]
          }
        ],
        "label": "leg"
      },
      "skirt_front_2": {
        "translation": [
          -70.04967760282253,
          26.58691363979149,
          25.0
        ],
        "rotation": [
          0.0,
          0.0,
          0.0
        ],
        "vertices": [
          [
            0,
            0
          ],
          [
            140.25301122546745,
            0
          ],
          [
            136.25301122546745,
            6.521239123673589
          ],
          [
            4.0,
            6.521239123673589
          ]
        ],
        "edges": [
          {
            "endpoints": [
              0,
              1
            ]
          },
          {
            "endpoints": [
              1,
              2
            ]
          },
          {
            "endpoints": [
              2,
              3
            ]
          },
          {
            "endpoints": [
              3,
              0
            ]
          }
        ],
        "label": "leg"
      },
      "skirt_front_1": {
        "translation": [
          -54.07798993998755,
          38.108152763465085,
          25.0
        ],
        "rotation": [
          0.0,
          0.0,
          0.0
        ],
        "vertices": [
          [
            0,
            0
          ],
          [
            108.53632976862285,
            0
          ],
          [
            104.53632976862285,
            6.521239123673589
          ],
          [
            4.0,
            6.521239123673589
          ]
        ],
        "edges": [
          {
            "endpoints": [
              0,
              1
            ]
          },
          {
            "endpoints": [
              1,
              2
            ]
          },
          {
            "endpoints": [
              2,
              3
            ]
          },
          {
            "endpoints": [
              3,
              0
            ]
          }
        ],
        "label": "leg"
      },
      "skirt_back_1": {
        "translation": [
          -59.07798993998755,
          38.108152763465085,
          -20.0
        ],
        "rotation": [
          0.0,
          0.0,
          0.0
        ],
        "vertices": [
          [
            0,
            0
          ],
          [
            4.0,
            6.521239123673589
          ],
          [
            114.1559798799751,
            6.521239123673589
          ],
          [
            118.1559798799751,
            0
          ]
        ],
        "edges": [
          {
            "endpoints": [
              0,
              1
            ]
          },
          {
            "endpoints": [
              1,
              2
            ]
          },
          {
            "endpoints": [
              2,
              3
            ]
          },
          {
            "endpoints": [
              3,
              0
            ]
          }
        ],
        "label": "leg"
      },
      "skirt_back_3": {
        "translation": [
          -96.21919315816848,
          15.065674516117895,
          -20.0
        ],
        "rotation": [
          0.0,
          0.0,
          0.0
        ],
        "vertices": [
          [
            0,
            0
          ],
          [
            4.0,
            6.521239123673589
          ],
          [
            188.43838631633696,
            6.521239123673589
          ],
          [
            192.43838631633696,
            0
          ]
        ],
        "edges": [
          {
            "endpoints": [
              0,
              1
            ]
          },
          {
            "endpoints": [
              1,
              2
            ]
          },
          {
            "endpoints": [
              2,
              3
            ]
          },
          {
            "endpoints": [
              3,
              0
            ]
          }
        ],
        "label": "leg"
      },
      "skirt_front_3": {
        "translation": [
          -88.21919315816848,
          15.065674516117895,
          25.0
        ],
        "rotation": [
          0.0,
          0.0,
          0.0
        ],
        "vertices": [
          [
            0,
            0
          ],
          [
            177.94579185615476,
            0
          ],
          [
            173.94579185615476,
            6.521239123673589
          ],
          [
            4.0,
            6.521239123673589
          ]
        ],
        "edges": [
          {
            "endpoints": [
              0,
              1
            ]
          },
          {
            "endpoints": [
              1,
              2
            ]
          },
          {
            "endpoints": [
              2,
              3
            ]
          },
          {
            "endpoints": [
              3,
              0
            ]
          }
        ],
        "label": "leg"
      }
    },
    "stitches": [
      [
        {
          "panel": "sl_left_cuff_skirt_f",
          "edge": 0
        },
        {
          "panel": "sl_left_cuff_skirt_b",
          "edge": 3
        }
      ],
      [
        {
          "panel": "sl_left_cuff_skirt_f",
          "edge": 2
        },
        {
          "panel": "sl_left_cuff_skirt_b",
          "edge": 1
        }
      ],
      [
        {
          "panel": "sl_left_cuff_f",
          "edge": 0
        },
        {
          "panel": "sl_left_cuff_b",
          "edge": 3
        }
      ],
      [
        {
          "panel": "sl_left_cuff_f",
          "edge": 2
        },
        {
          "panel": "sl_left_cuff_b",
          "edge": 1
        }
      ],
      [
        {
          "panel": "sl_left_cuff_f",
          "edge": 3
        },
        {
          "panel": "sl_left_cuff_skirt_f",
          "edge": 1
        }
      ],
      [
        {
          "panel": "sl_left_cuff_b",
          "edge": 0
        },
        {
          "panel": "sl_left_cuff_skirt_b",
          "edge": 2
        }
      ],
      [
        {
          "panel": "left_sleeve_f",
          "edge": 0
        },
        {
          "panel": "left_sleeve_b",
          "edge": 4
        }
      ],
      [
        {
          "panel": "left_sleeve_f",
          "edge": 2
        },
        {
          "panel": "left_sleeve_b",
          "edge": 1
        }
      ],
      [
        {
          "panel": "sl_left_cuff_f",
          "edge": 1
        },
        {
          "panel": "left_sleeve_f",
          "edge": 3
        }
      ],
      [
        {
          "panel": "sl_left_cuff_b",
          "edge": 2
        },
        {
          "panel": "left_sleeve_b",
          "edge": 0
        }
      ],
      [
        {
          "panel": "left_btorso",
          "edge": 9
        },
        {
          "panel": "left_btorso",
          "edge": 8
        }
      ],
      [
        {
          "panel": "left_btorso",
          "edge": 12
        },
        {
          "panel": "left_btorso",
          "edge": 11
        }
      ],
      [
        {
          "panel": "left_ftorso",
          "edge": 5
        },
        {
          "panel": "left_ftorso",
          "edge": 6
        }
      ],
      [
        {
          "panel": "left_ftorso",
          "edge": 1
        },
        {
          "panel": "left_ftorso",
          "edge": 2
        }
      ],
      [
        {
          "panel": "left_sleeve_f",
          "edge": 1
        },
        {
          "panel": "left_ftorso",
          "edge": 8
        }
      ],
      [
        {
          "panel": "left_sleeve_b",
          "edge": 3
        },
        {
          "panel": "left_ftorso",
          "edge": 9
        }
      ],
      [
        {
          "panel": "left_sleeve_b",
          "edge": 2
        },
        {
          "panel": "left_btorso",
          "edge": 4
        }
      ],
      [
        {
          "panel": "left_ftorso",
          "edge": 10
        },
        {
          "panel": "left_btorso",
          "edge": 3
        }
      ],
      [
        {
          "panel": "left_ftorso",
          "edge": 4
        },
        {
          "panel": "left_btorso",
          "edge": 6
        }
      ],
      [
        {
          "panel": "left_ftorso",
          "edge": 7
        },
        {
          "panel": "left_btorso",
          "edge": 5
        }
      ],
      [
        {
          "panel": "right_btorso",
          "edge": 4
        },
        {
          "panel": "right_btorso",
          "edge": 5
        }
      ],
      [
        {
          "panel": "right_btorso",
          "edge": 1
        },
        {
          "panel": "right_btorso",
          "edge": 2
        }
      ],
      [
        {
          "panel": "right_ftorso",
          "edge": 6
        },
        {
          "panel": "right_ftorso",
          "edge": 5
        }
      ],
      [
        {
          "panel": "right_ftorso",
          "edge": 10
        },
        {
          "panel": "right_ftorso",
          "edge": 9
        }
      ],
      [
        {
          "panel": "right_ftorso",
          "edge": 2
        },
        {
          "panel": "right_btorso",
          "edge": 10
        }
      ],
      [
        {
          "panel": "right_ftorso",
          "edge": 7
        },
        {
          "panel": "right_btorso",
          "edge": 7
        }
      ],
      [
        {
          "panel": "right_ftorso",
          "edge": 4
        },
        {
          "panel": "right_btorso",
          "edge": 8
        }
      ],
      [
        {
          "panel": "right_ftorso",
          "edge": 0
        },
        {
          "panel": "left_ftorso",
          "edge": 12
        }
      ],
      [
        {
          "panel": "right_btorso",
          "edge": 12
        },
        {
          "panel": "left_btorso",
          "edge": 0
        }
      ],
      [
        {
          "panel": "skirt_back",
          "edge": 3
        },
        {
          "panel": "skirt_back",
          "edge": 4
        }
      ],
      [
        {
          "panel": "skirt_back",
          "edge": 6
        },
        {
          "panel": "skirt_back",
          "edge": 7
        }
      ],
      [
        {
          "panel": "skirt_back",
          "edge": 10
        },
        {
          "panel": "skirt_back",
          "edge": 11
        }
      ],
      [
        {
          "panel": "skirt_back",
          "edge": 13
        },
        {
          "panel": "skirt_back",
          "edge": 14
        }
      ],
      [
        {
          "panel": "skirt_front",
          "edge": 8
        },
        {
          "panel": "skirt_back",
          "edge": 0
        }
      ],
      [
        {
          "panel": "skirt_front",
          "edge": 7
        },
        {
          "panel": "skirt_back",
          "edge": 1
        }
      ],
      [
        {
          "panel": "skirt_front",
          "edge": 2
        },
        {
          "panel": "skirt_back",
          "edge": 16
        }
      ],
      [
        {
          "panel": "skirt_front",
          "edge": 1
        },
        {
          "panel": "skirt_back",
          "edge": 17
        }
      ],
      [
        {
          "panel": "skirt_front_0",
          "edge": 3
        },
        {
          "panel": "skirt_back_0",
          "edge": 0
        }
      ],
      [
        {
          "panel": "skirt_front_0",
          "edge": 1
        },
        {
          "panel": "skirt_back_0",
          "edge": 2
        }
      ],
      [
        {
          "panel": "skirt_front_2",
          "edge": 3
        },
        {
          "panel": "skirt_back_2",
          "edge": 0
        }
      ],
      [
        {
          "panel": "skirt_front_2",
          "edge": 1
        },
        {
          "panel": "skirt_back_2",
          "edge": 2
        }
      ],
      [
        {
          "panel": "skirt_front_1",
          "edge": 3
        },
        {
          "panel": "skirt_back_1",
          "edge": 0
        }
      ],
      [
        {
          "panel": "skirt_front_1",
          "edge": 1
        },
        {
          "panel": "skirt_back_1",
          "edge": 2
        }
      ],
      [
        {
          "panel": "skirt_front_3",
          "edge": 3
        },
        {
          "panel": "skirt_back_3",
          "edge": 0
        }
      ],
      [
        {
          "panel": "skirt_front_3",
          "edge": 1
        },
        {
          "panel": "skirt_back_3",
          "edge": 2
        }
      ],
      [
        {
          "panel": "skirt_front",
          "edge": 0
        },
        {
          "panel": "skirt_front_0",
          "edge": 2
        }
      ],
      [
        {
          "panel": "skirt_back",
          "edge": 18
        },
        {
          "panel": "skirt_back_0",
          "edge": 1
        }
      ],
      [
        {
          "panel": "skirt_front_0",
          "edge": 0
        },
        {
          "panel": "skirt_front_1",
          "edge": 2
        }
      ],
      [
        {
          "panel": "skirt_back_0",
          "edge": 3
        },
        {
          "panel": "skirt_back_1",
          "edge": 1
        }
      ],
      [
        {
          "panel": "skirt_front_1",
          "edge": 0
        },
        {
          "panel": "skirt_front_2",
          "edge": 2
        }
      ],
      [
        {
          "panel": "skirt_back_1",
          "edge": 3
        },
        {
          "panel": "skirt_back_2",
          "edge": 1
        }
      ],
      [
        {
          "panel": "skirt_front_2",
          "edge": 0
        },
        {
          "panel": "skirt_front_3",
          "edge": 2
        }
      ],
      [
        {
          "panel": "skirt_back_2",
          "edge": 3
        },
        {
          "panel": "skirt_back_3",
          "edge": 1
        }
      ],
      [
        {
          "panel": "right_ftorso",
          "edge": 8
        },
        {
          "panel": "skirt_front",
          "edge": 6
        }
      ],
      [
        {
          "panel": "right_ftorso",
          "edge": 11
        },
        {
          "panel": "skirt_front",
          "edge": 5
        }
      ],
      [
        {
          "panel": "left_ftorso",
          "edge": 0
        },
        {
          "panel": "skirt_front",
          "edge": 4
        }
      ],
      [
        {
          "panel": "left_ftorso",
          "edge": 3
        },
        {
          "panel": "skirt_front",
          "edge": 3
        }
      ],
      [
        {
          "panel": "left_btorso",
          "edge": 7
        },
        {
          "panel": "skirt_back",
          "edge": 15
        }
      ],
      [
        {
          "panel": "left_btorso",
          "edge": 10
        },
        {
          "panel": "skirt_back",
          "edge": 12
        }
      ],
      [
        {
          "panel": "left_btorso",
          "edge": 13
        },
        {
          "panel": "skirt_back",
          "edge": 9
        }
      ],
      [
        {
          "panel": "right_btorso",
          "edge": 0
        },
        {
          "panel": "skirt_back",
          "edge": 8
        }
      ],
      [
        {
          "panel": "right_btorso",
          "edge": 3
        },
        {
          "panel": "skirt_back",
          "edge": 5
        }
      ],
      [
        {
          "panel": "right_btorso",
          "edge": 6
        },
        {
          "panel": "skirt_back",
          "edge": 2
        }
      ]
    ],
    "panel_order": [
      "right_btorso",
      "right_ftorso",
      "skirt_back_3",
      "skirt_front_3",
      "skirt_back_2",
      "skirt_front_2",
      "skirt_back_1",
      "skirt_front_1",
      "skirt_back_0",
      "skirt_front_0",
      "skirt_back",
      "skirt_front",
      "left_btorso",
      "left_ftorso",
      "left_sleeve_b",
      "sl_left_cuff_b",
      "left_sleeve_f",
      "sl_left_cuff_f",
      "sl_left_cuff_skirt_b",
      "sl_left_cuff_skirt_f"
    ]
  },
  "parameters": {},
  "parameter_order": [],
  "properties": {
    "curvature_coords": "relative",
    "normalize_panel_translation": false,
    "normalized_edge_loops": true,
    "units_in_meter": 100
  }
}