{
  "pattern": {
    "panels": {
      "right_sleeve_b": {
        "translation": [
          -61.56027638510071,
          104.24584084693979,
          -12.5
        ],
        "rotation": [
          0.0,
          0.0,
          45.482999999999976
        ],
        "vertices": [
          [
            0,
            0
          ],
          [
            51.96470953238541,
            0.0
          ],
          [
            51.955475016685,
            -0.7029009081778526
          ],
          [
            29.104142324727672,
            -31.462440394834488
          ],
          [
            0,
            -28.78246453672184
          ]
        ],
        "edges": [
          {
            "endpoints": [
              0,
              1
            ]
          },
          {
            "endpoints": [
              1,
              2
            ],
            "curvature": {
              "type": "cubic",
              "params": [
                [
                  0.3297984161408044,
                  0.0015071944002226978
                ],
                [
                  0.6631169152183544,
                  0.0015135193370390254
                ]
              ]
            }
          },
          {
            "endpoints": [
              2,
              3
            ],
            "curvature": {
              "type": "cubic",
              "params": [
                [
                  0.563662262436517,
                  0.41326009380188977
                ],
                [
                  0.6556765809476279,
                  -0.01966325780121191
                ]
              ]
            }
          },
          {
            "endpoints": [
              3,
              4
            ]
          },
          {
            "endpoints": [
              4,
              0
            ]
          }
        ],
        "label": "arm"
      },
      "sl_right_cuff_b": {
        "translation": [
          -64.85448222483056,
          100.89562157341236,
          -12.5
        ],
        "rotation": [
          0.0,
          0.0,
          -44.516999999999996
        ],
        "vertices": [
          [
            0,
            0
          ],
          [
            0,
            2.6984850000000002
          ],
          [
            11.151366798088002,
            2.6984850000000002
          ],
          [
            11.151366798088002,
            0
          ]
        ],
        "edges": [
          {
            "endpoints": [
              0,
              1
            ]
          },
          {
            "endpoints": [
              1,
              2
            ]
          },
          {
            "endpoints": [
              2,
              3
            ]
          },
          {
            "endpoints": [
              3,
              0
            ]
          }
        ],
        "label": "arm"
      },
      "sl_right_cuff_f": {
        "translation": [
          -64.85448222483056,
          100.89562157341236,
          17.5
        ],
        "rotation": [
          0.0,
          0.0,
          -44.516999999999996
        ],
        "vertices": [
          [
            0,
            0
          ],
          [
            11.151366798088002,
            0
          ],
          [
            11.151366798088002,
            2.6984850000000002
          ],
          [
            0,
            2.6984850000000002
          ]
        ],
        "edges": [
          {
            "endpoints": [
              0,
              1
            ]
          },
          {
            "endpoints": [
              1,
              2
            ]
          },
          {
            "endpoints": [
              2,
              3
            ]
          },
          {
            "endpoints": [
              3,
              0
            ]
          }
        ],
        "label": "arm"
      },
      "sl_right_cuff_skirt_f": {
        "translation": [
          -75.22207107018366,
          104.50052305508137,
          17.5
        ],
        "rotation": [
          0.0,
          0.0,
          -44.516999999999996
        ],
        "vertices": [
          [
            0,
            0
          ],
          [
            30.991372026273257,
            0
          ],
          [
            21.07136941218063,
            2.6984850000000002
          ],
          [
            9.920002614092628,
            2.6984850000000002
          ]
        ],
        "edges": [
          {
            "endpoints": [
              0,
              1
            ]
          },
          {
            "endpoints": [
              1,
              2
            ]
          },
          {
            "endpoints": [
              2,
              3
            ]
          },
          {
            "endpoints": [
              3,
              0
            ]
          }
        ],
        "label": "arm"
      },
      "sl_right_cuff_skirt_b": {
        "translation": [
          -75.22207107018366,
          104.50052305508137,
          -12.5
        ],
        "rotation": [
          0.0,
          0.0,
          -44.516999999999996
        ],
        "vertices": [
          [
            0,
            0
          ],
          [
            9.920002614092628,
            2.6984850000000002
          ],
          [
            21.07136941218063,
            2.6984850000000002
          ],
          [
            30.991372026273257,
            0
          ]
        ],
        "edges": [
          {
            "endpoints": [
              0,
              1
            ]
          },
          {
            "endpoints": [
              1,
              2
            ]
          },
          {
            "endpoints": [
              2,
              3
            ]
          },
          {
            "endpoints": [
              3,
              0
            ]
          }
        ],
        "label": "arm"
      },
      "right_sleeve_f": {
        "translation": [
          -61.56027638510071,
          104.24584084693979,
          17.5
        ],
        "rotation": [
          0.0,
          0.0,
          45.482999999999976
        ],
        "vertices": [
          [
            0,
            0
          ],
          [
            0,
            -28.782464536721882
          ],
          [
            29.104142324727672,
            -31.462440394834534
          ],
          [
            51.96470953238541,
            0.0
          ]
        ],
        "edges": [
          {
            "endpoints": [
              0,
              1
            ]
          },
          {
            "endpoints": [
              1,
              2
            ]
          },
          {
            "endpoints": [
              2,
              3
            ],
            "curvature": {
              "type": "cubic",
              "params": [
                [
                  0.3478110409320066,
                  0.024922802756911454
                ],
                [
                  0.415464245885295,
                  -0.4324224902978901
                ]
              ]
            }
          },
          {
            "endpoints": [
              3,
              0
            ]
          }
        ],
        "label": "arm"
      },
      "right_ftorso": {
        "translation": [
          0.0,
          95.7946097142119,
          30.0
        ],
        "rotation": [
          0.0,
          0.0,
          0.0
        ],
        "vertices": [
          [
            0,
            0
          ],
          [
            0.0,
            29.920183987398115
          ],
          [
            -10.8188,
            45.568743815994225
          ],
          [
            -16.193704806737728,
            43.43223266519252
          ],
          [
            -16.269177736641385,
            42.7382737050314
          ],
          [
            -34.22531088189355,
            9.57665763436674
          ],
          [
            -36.45249757156336,
            0
          ]
        ],
        "edges": [
          {
            "endpoints": [
              0,
              1
            ]
          },
          {
            "endpoints": [
              1,
              2
            ],
            "label": "right_collar",
            "curvature": {
              "type": "cubic",
              "params": [
                [
                  0.19999999999999996,
                  -0.3
                ],
                [
                  0.6,
                  0.3
                ]
              ]
            }
          },
          {
            "endpoints": [
              2,
              3
            ]
          },
          {
            "endpoints": [
              3,
              4
            ],
            "curvature": {
              "type": "cubic",
              "params": [
                [
                  0.334771763335862,
                  -0.00018462224867657882
                ],
                [
                  0.6681070732540987,
                  -0.00017255750918342507
                ]
              ]
            }
          },
          {
            "endpoints": [
              4,
              5
            ],
            "curvature": {
              "type": "cubic",
              "params": [
                [
                  0.49689985085186633,
                  0.20336030910618325
                ],
                [
                  0.7964513144127358,
                  0.3505852315474322
                ]
              ]
            }
          },
          {
            "endpoints": [
              5,
              6
            ]
          },
          {
            "endpoints": [
              6,
              0
            ]
          }
        ],
        "label": "body"
      },
      "right_collar_front": {
        "translation": [
          -12.0,
          157.6638,
          35.0
        ],
        "rotation": [
          0.0,
          0.0,
          0.0
        ],
        "vertices": [
          [
            0,
            0
          ],
          [
            6,
            -20.53779196302502
          ],
          [
            6,
            0
          ]
        ],
        "edges": [
          {
            "endpoints": [
              0,
              1
            ],
            "curvature": {
              "type": "quadratic",
              "params": [
                [
                  0.30000000000000004,
                  -0.2
                ]
              ]
            }
          },
          {
            "endpoints": [
              1,
              2
            ]
          },
          {
            "endpoints": [
              2,
              0
            ]
          }
        ],
        "label": "body"
      },
      "right_collar_back": {
        "translation": [
          -17.00386421503373,
          153.34876108569256,
          -10.0
        ],
        "rotation": [
          89.99999999999999,
          45.0,
          0.0
        ],
        "vertices": [
          [
            -0.10238655478127434,
            0
          ],
          [
            12.102386554781274,
            0
          ],
          [
            14.879446819604505,
            -5.318640454621832
          ],
          [
            -2.879446819604505,
            -5.318640454621832
          ]
        ],
        "edges": [
          {
            "endpoints": [
              0,
              1
            ],
            "curvature": {
              "type": "circle",
              "params": [
                13.184560591816416,
                0,
                1
              ]
            }
          },
          {
            "endpoints": [
              1,
              2
            ]
          },
          {
            "endpoints": [
              2,
              3
            ],
            "curvature": {
              "type": "circle",
              "params": [
                19.184560591816414,
                0,
                0
              ]
            }
          },
          {
            "endpoints": [
              3,
              0
            ]
          }
        ],
        "label": "body"
      },
      "right_btorso": {
        "translation": [
          0.0,
          95.8392139088772,
          -25.0
        ],
        "rotation": [
          0.0,
          0.0,
          0.0
        ],
        "vertices": [
          [
            0,
            0
          ],
          [
            -33.31594451930259,
            0
          ],
          [
            -31.362649405816047,
            9.399974490253445
          ],
          [
            -16.525978955170846,
            43.25554952107923
          ],
          [
            -10.8188,
            45.524139569975745
          ],
          [
            0.0,
            39.87524116268419
          ]
        ],
        "edges": [
          {
            "endpoints": [
              0,
              1
            ]
          },
          {
            "endpoints": [
              1,
              2
            ]
          },
          {
            "endpoints": [
              2,
              3
            ],
            "label": "right_armhole",
            "curvature": {
              "type": "cubic",
              "params": [
                [
                  0.19999999999999996,
                  -0.35
                ],
                [
                  0.5,
                  -0.2
                ]
              ]
            }
          },
          {
            "endpoints": [
              3,
              4
            ]
          },
          {
            "endpoints": [
              4,
              5
            ],
            "label": "right_collar",
            "curvature": {
              "type": "circle",
              "params": [
                13.184560591816423,
                0,
                1
              ]
            }
          },
          {
            "endpoints": [
              5,
              0
            ]
          }
        ],
        "label": "body"
      },
      "left_collar_front": {
        "translation": [
          12.0,
          157.6638,
          35.0
        ],
        "rotation": [
          0.0,
          0.0,
          0.0
        ],
        "vertices": [
          [
            0.0,
            0.0
          ],
          [
            -6.0,
            0.0
          ],
          [
            -6.0,
            -20.53779196302502
          ]
        ],
        "edges": [
          {
            "endpoints": [
              0,
              1
            ]
          },
          {
            "endpoints": [
              1,
              2
            ]
          },
          {
            "endpoints": [
              2,
              0
            ],
            "curvature": {
              "type": "quadratic",
              "params": [
                [
                  0.7,
                  -0.2
                ]
              ]
            }
          }
        ],
        "label": "body"
      },
      "left_collar_back": {
        "translation": [
          17.00386421503373,
          153.34876108569256,
          -10.0
        ],
        "rotation": [
          89.99999999999999,
          -45.0,
          0.0
        ],
        "vertices": [
          [
            0.10238655478127434,
            0.0
          ],
          [
            2.879446819604505,
            -5.318640454621832
          ],
          [
            -14.879446819604505,
            -5.318640454621832
          ],
          [
            -12.102386554781274,
            0.0
          ]
        ],
        "edges": [
          {
            "endpoints": [
              0,
              1
            ]
          },
          {
            "endpoints": [
              1,
              2
            ],
            "curvature": {
              "type": "circle",
              "params": [
                19.184560591816414,
                0,
                0
              ]
            }
          },
          {
            "endpoints": [
              2,
              3
            ]
          },
          {
            "endpoints": [
              3,
              0
            ],
            "curvature": {
              "type": "circle",
              "params": [
                13.184560591816416,
                0,
                1
              ]
            }
          }
        ],
        "label": "body"
      },
      "left_btorso": {
        "translation": [
          0.0,
          95.8392139088772,
          -25.0
        ],
        "rotation": [
          0.0,
          0.0,
          0.0
        ],
        "vertices": [
          [
            0.0,
            0.0
          ],
          [
            0.0,
            39.87524116268419
          ],
          [
            10.8188,
            45.524139569975745
          ],
          [
            16.525978955170846,
            43.25554952107923
          ],
          [
            31.362649405816047,
            9.399974490253445
          ],
          [
            33.31594451930259,
            0.0
          ]
        ],
        "edges": [
          {
            "endpoints": [
              0,
              1
            ]
          },
          {
            "endpoints": [
              1,
              2
            ],
            "label": "left_collar",
            "curvature": {
              "type": "circle",
              "params": [
                13.184560591816423,
                0,
                1
              ]
            }
          },
          {
            "endpoints": [
              2,
              3
            ]
          },
          {
            "endpoints": [
              3,
              4
            ],
            "label": "left_armhole",
            "curvature": {
              "type": "cubic",
              "params": [
                [
                  0.5,
                  -0.2
                ],
                [
                  0.8,
                  -0.35
                ]
              ]
            }
          },
          {
            "endpoints": [
              4,
              5
            ]
          },
          {
            "endpoints": [
              5,
              0
            ]
          }
        ],
        "label": "body"
      },
      "left_ftorso": {
        "translation": [
          0.0,
          95.7946097142119,
          30.0
        ],
        "rotation": [
          0.0,
          0.0,
          0.0
        ],
        "vertices": [
          [
            0.0,
            0.0
          ],
          [
            36.45249757156336,
            0.0
          ],
          [
            34.22531088189355,
            9.57665763436674
          ],
          [
            16.269177736641385,
            42.7382737050314
          ],
          [
            16.193704806737728,
            43.43223266519252
          ],
          [
            10.8188,
            45.568743815994225
          ],
          [
            0.0,
            29.920183987398115
          ]
        ],
        "edges": [
          {
            "endpoints": [
              0,
              1
            ]
          },
          {
            "endpoints": [
              1,
              2
            ]
          },
          {
            "endpoints": [
              2,
              3
            ],
            "curvature": {
              "type": "cubic",
              "params": [
                [
                  0.20354868558726424,
                  0.3505852315474322
                ],
                [
                  0.5031001491481337,
                  0.20336030910618325
                ]
              ]
            }
          },
          {
            "endpoints": [
              3,
              4
            ],
            "curvature": {
              "type": "cubic",
              "params": [
                [
                  0.3318929267459013,
                  -0.00017255750918342507
                ],
                [
                  0.665228236664138,
                  -0.00018462224867657882
                ]
              ]
            }
          },
          {
            "endpoints": [
              4,
              5
            ]
          },
          {
            "endpoints": [
              5,
              6
            ],
            "label": "left_collar",
            "curvature": {
              "type": "cubic",
              "params": [
                [
                  0.4,
                  0.3
                ],
                [
                  0.8,
                  -0.3
                ]
              ]
            }
          },
          {
            "endpoints": [
              6,
              0
            ]
          }
        ],
        "label": "body"
      },
      "sl_left_cuff_f": {
        "translation": [
          64.85448222483056,
          100.89562157341236,
          17.5
        ],
        "rotation": [
          0.0,
          0.0,
          44.517000000000024
        ],
        "vertices": [
          [
            0.0,
            0.0
          ],
          [
            0.0,
            2.6984850000000002
          ],
          [
            -11.151366798088002,
            2.6984850000000002
          ],
          [
            -11.151366798088002,
            0.0
          ]
        ],
        "edges": [
          {
            "endpoints": [
              0,
              1
            ]
          },
          {
            "endpoints": [
              1,
              2
            ]
          },
          {
            "endpoints": [
              2,
              3
            ]
          },
          {
            "endpoints": [
              3,
              0
            ]
          }
        ],
        "label": "arm"
      },
      "sl_left_cuff_b": {
        "translation": [
          64.85448222483056,
          100.89562157341236,
          -12.5
        ],
        "rotation": [
          0.0,
          0.0,
          44.517000000000024
        ],
        "vertices": [
          [
            0.0,
            0.0
          ],
          [
            -11.151366798088002,
            0.0
          ],
          [
            -11.151366798088002,
            2.6984850000000002
          ],
          [
            0.0,
            2.6984850000000002
          ]
        ],
        "edges": [
          {
            "endpoints": [
              0,
              1
            ]
          },
          {
            "endpoints": [
              1,
              2
            ]
          },
          {
            "endpoints": [
              2,
              3
            ]
          },
          {
            "endpoints": [
              3,
              0
            ]
          }
        ],
        "label": "arm"
      },
      "sl_left_cuff_skirt_f": {
        "translation": [
          75.22207107018366,
          104.50052305508137,
          17.5
        ],
        "rotation": [
          0.0,
          0.0,
          44.517000000000024
        ],
        "vertices": [
          [
            0.0,
            0.0
          ],
          [
            -9.920002614092628,
            2.6984850000000002
          ],
          [
            -21.07136941218063,
            2.6984850000000002
          ],
          [
            -30.991372026273257,
            0.0
          ]
        ],
        "edges": [
          {
            "endpoints": [
              0,
              1
            ]
          },
          {
            "endpoints": [
              1,
              2
            ]
          },
          {
            "endpoints": [
              2,
              3
            ]
          },
          {
            "endpoints": [
              3,
              0
            ]
          }
        ],
        "label": "arm"
      },
      "sl_left_cuff_skirt_b": {
        "translation": [
          75.22207107018366,
          104.50052305508137,
          -12.5
        ],
        "rotation": [
          0.0,
          0.0,
          44.517000000000024
        ],
        "vertices": [
          [
            0.0,
            0.0
          ],
          [
            -30.991372026273257,
            0.0
          ],
          [
            -21.07136941218063,
            2.6984850000000002
          ],
          [
            -9.920002614092628,
            2.6984850000000002
          ]
        ],
        "edges": [
          {
            "endpoints": [
              0,
              1
            ]
          },
          {
            "endpoints": [
              1,
              2
            ]
          },
          {
            "endpoints": [
              2,
              3
            ]
          },
          {
            "endpoints": [
              3,
              0
            ]
          }
        ],
        "label": "arm"
      },
      "left_sleeve_b": {
        "translation": [
          61.56027638510071,
          104.24584084693981,
          -12.5
        ],
        "rotation": [
          0.0,
          0.0,
          -45.482999999999976
        ],
        "vertices": [
          [
            0.0,
            0.0
          ],
          [
            0.0,
            -28.78246453672184
          ],
          [
            -29.104142324727672,
            -31.462440394834488
          ],
          [
            -51.955475016685,
            -0.7029009081778526
          ],
          [
            -51.96470953238541,
            0.0
          ]
        ],
        "edges": [
          {
            "endpoints": [
              0,
              1
            ]
          },
          {
            "endpoints": [
              1,
              2
            ]
          },
          {
            "endpoints": [
              2,
              3
            ],
            "curvature": {
              "type": "cubic",
              "params": [
                [
                  0.34432341905237207,
                  -0.01966325780121191
                ],
                [
                  0.43633773756348304,
                  0.41326009380188977
                ]
              ]
            }
          },
          {
            "endpoints": [
              3,
              4
            ],
            "curvature": {
              "type": "cubic",
              "params": [
                [
                  0.33688308478164564,
                  0.0015135193370390254
                ],
                [
                  0.6702015838591956,
                  0.0015071944002226978
                ]
              ]
            }
          },
          {
            "endpoints": [
              4,
              0
            ]
          }
        ],
        "label": "arm"
      },
      "left_sleeve_f": {
        "translation": [
          61.56027638510071,
          104.24584084693981,
          17.5
        ],
        "rotation": [
          0.0,
          0.0,
          -45.482999999999976
        ],
        "vertices": [
          [
            0.0,
            0.0
          ],
          [
            -51.96470953238541,
            0.0
          ],
          [
            -29.104142324727672,
            -31.462440394834534
          ],
          [
            0.0,
            -28.782464536721882
          ]
        ],
        "edges": [
          {
            "endpoints": [
              0,
              1
            ]
          },
          {
            "endpoints": [
              1,
              2
            ],
            "curvature": {
              "type": "cubic",
              "params": [
                [
                  0.5845357541147049,
                  -0.4324224902978901
                ],
                [
                  0.6521889590679935,
                  0.024922802756911454
                ]
              ]
            }
          },
          {
            "endpoints": [
              2,
              3
            ]
          },
          {
            "endpoints": [
              3,
              0
            ]
          }
        ],
        "label": "arm"
      },
      "wb_back": {
        "translation": [
          -19.5679,
          86.12017181154454,
          -15.0
        ],
        "rotation": [
          0.0,
          0.0,
          0.0
        ],
        "vertices": [
          [
            0,
            0
          ],
          [
            0,
            4.69674
          ],
          [
            19.5679,
            4.69674
          ],
          [
            39.1358,
            4.69674
          ],
          [
            39.1358,
            0
          ]
        ],
        "edges": [
          {
            "endpoints": [
              0,
              1
            ]
          },
          {
            "endpoints": [
              1,
              2
            ],
            "label": "lower_interface"
          },
          {
            "endpoints": [
              2,
              3
            ],
            "label": "lower_interface"
          },
          {
            "endpoints": [
              3,
              4
            ]
          },
          {
            "endpoints": [
              4,
              0
            ]
          }
        ],
        "label": "body"
      },
      "wb_front": {
        "translation": [
          -22.598999999999997,
          86.12017181154454,
          20.0
        ],
        "rotation": [
          0.0,
          0.0,
          0.0
        ],
        "vertices": [
          [
            0,
            0
          ],
          [
            45.19799999999999,
            0
          ],
          [
            45.19799999999999,
            4.69674
          ],
          [
            22.598999999999997,
            4.69674
          ],
          [
            0,
            4.69674
          ]
        ],
        "edges": [
          {
            "endpoints": [
              0,
              1
            ]
          },
          {
            "endpoints": [
              1,
              2
            ]
          },
          {
            "endpoints": [
              2,
              3
            ],
            "label": "lower_interface"
          },
          {
            "endpoints": [
              3,
              4
            ],
            "label": "lower_interface"
          },
          {
            "endpoints": [
              4,
              0
            ]
          }
        ],
        "label": "body"
      }
    },
    "stitches": [
      [
        {
          "panel": "sl_right_cuff_f",
          "edge": 3
        },
        {
          "panel": "sl_right_cuff_b",
          "edge": 0
        }
      ],
      [
        {
          "panel": "sl_right_cuff_f",
          "edge": 1
        },
        {
          "panel": "sl_right_cuff_b",
          "edge": 2
        }
      ],
      [
        {
          "panel": "sl_right_cuff_skirt_f",
          "edge": 3
        },
        {
          "panel": "sl_right_cuff_skirt_b",
          "edge": 0
        }
      ],
      [
        {
          "panel": "sl_right_cuff_skirt_f",
          "edge": 1
        },
        {
          "panel": "sl_right_cuff_skirt_b",
          "edge": 2
        }
      ],
      [
        {
          "panel": "sl_right_cuff_f",
          "edge": 0
        },
        {
          "panel": "sl_right_cuff_skirt_f",
          "edge": 2
        }
      ],
      [
        {
          "panel": "sl_right_cuff_b",
          "edge": 3
        },
        {
          "panel": "sl_right_cuff_skirt_b",
          "edge": 1
        }
      ],
      [
        {
          "panel": "right_sleeve_f",
          "edge": 3
        },
        {
          "panel": "right_sleeve_b",
          "edge": 0
        }
      ],
      [
        {
          "panel": "right_sleeve_f",
          "edge": 1
        },
        {
          "panel": "right_sleeve_b",
          "edge": 3
        }
      ],
      [
        {
          "panel": "sl_right_cuff_f",
          "edge": 2
        },
        {
          "panel": "right_sleeve_f",
          "edge": 0
        }
      ],
      [
        {
          "panel": "sl_right_cuff_b",
          "edge": 1
        },
        {
          "panel": "right_sleeve_b",
          "edge": 4
        }
      ],
      [
        {
          "panel": "right_collar_front",
          "edge": 2
        },
        {
          "panel": "right_collar_back",
          "edge": 3
        }
      ],
      [
        {
          "panel": "right_sleeve_f",
          "edge": 2
        },
        {
          "panel": "right_ftorso",
          "edge": 4
        }
      ],
      [
        {
          "panel": "right_sleeve_b",
          "edge": 1
        },
        {
          "panel": "right_ftorso",
          "edge": 3
        }
      ],
      [
        {
          "panel": "right_sleeve_b",
          "edge": 2
        },
        {
          "panel": "right_btorso",
          "edge": 2
        }
      ],
      [
        {
          "panel": "right_ftorso",
          "edge": 1
        },
        {
          "panel": "right_collar_front",
          "edge": 1
        },
        "right_wrong"
      ],
      [
        {
          "panel": "right_btorso",
          "edge": 4
        },
        {
          "panel": "right_collar_back",
          "edge": 0
        },
        "right_wrong"
      ],
      [
        {
          "panel": "right_ftorso",
          "edge": 2
        },
        {
          "panel": "right_btorso",
          "edge": 3
        }
      ],
      [
        {
          "panel": "right_ftorso",
          "edge": 5
        },
        {
          "panel": "right_btorso",
          "edge": 1
        }
      ],
      [
        {
          "panel": "left_collar_front",
          "edge": 0
        },
        {
          "panel": "left_collar_back",
          "edge": 0
        }
      ],
      [
        {
          "panel": "sl_left_cuff_f",
          "edge": 0
        },
        {
          "panel": "sl_left_cuff_b",
          "edge": 3
        }
      ],
      [
        {
          "panel": "sl_left_cuff_f",
          "edge": 2
        },
        {
          "panel": "sl_left_cuff_b",
          "edge": 1
        }
      ],
      [
        {
          "panel": "sl_left_cuff_skirt_f",
          "edge": 0
        },
        {
          "panel": "sl_left_cuff_skirt_b",
          "edge": 3
        }
      ],
      [
        {
          "panel": "sl_left_cuff_skirt_f",
          "edge": 2
        },
        {
          "panel": "sl_left_cuff_skirt_b",
          "edge": 1
        }
      ],
      [
        {
          "panel": "sl_left_cuff_f",
          "edge": 3
        },
        {
          "panel": "sl_left_cuff_skirt_f",
          "edge": 1
        }
      ],
      [
        {
          "panel": "sl_left_cuff_b",
          "edge": 0
        },
        {
          "panel": "sl_left_cuff_skirt_b",
          "edge": 2
        }
      ],
      [
        {
          "panel": "left_sleeve_f",
          "edge": 0
        },
        {
          "panel": "left_sleeve_b",
          "edge": 4
        }
      ],
      [
        {
          "panel": "left_sleeve_f",
          "edge": 2
        },
        {
          "panel": "left_sleeve_b",
          "edge": 1
        }
      ],
      [
        {
          "panel": "sl_left_cuff_f",
          "edge": 1
        },
        {
          "panel": "left_sleeve_f",
          "edge": 3
        }
      ],
      [
        {
          "panel": "sl_left_cuff_b",
          "edge": 2
        },
        {
          "panel": "left_sleeve_b",
          "edge": 0
        }
      ],
      [
        {
          "panel": "left_sleeve_f",
          "edge": 1
        },
        {
          "panel": "left_ftorso",
          "edge": 2
        }
      ],
      [
        {
          "panel": "left_sleeve_b",
          "edge": 3
        },
        {
          "panel": "left_ftorso",
          "edge": 3
        }
      ],
      [
        {
          "panel": "left_sleeve_b",
          "edge": 2
        },
        {
          "panel": "left_btorso",
          "edge": 3
        }
      ],
      [
        {
          "panel": "left_ftorso",
          "edge": 5
        },
        {
          "panel": "left_collar_front",
          "edge": 1
        },
        "right_wrong"
      ],
      [
        {
          "panel": "left_btorso",
          "edge": 1
        },
        {
          "panel": "left_collar_back",
          "edge": 3
        },
        "right_wrong"
      ],
      [
        {
          "panel": "left_ftorso",
          "edge": 4
        },
        {
          "panel": "left_btorso",
          "edge": 2
        }
      ],
      [
        {
          "panel": "left_ftorso",
          "edge": 1
        },
        {
          "panel": "left_btorso",
          "edge": 4
        }
      ],
      [
        {
          "panel": "right_ftorso",
          "edge": 0
        },
        {
          "panel": "left_ftorso",
          "edge": 6
        }
      ],
      [
        {
          "panel": "right_btorso",
          "edge": 5
        },
        {
          "panel": "left_btorso",
          "edge": 0
        }
      ],
      [
        {
          "panel": "right_collar_back",
          "edge": 1
        },
        {
          "panel": "left_collar_back",
          "edge": 2
        }
      ],
      [
        {
          "panel": "wb_front",
          "edge": 4
        },
        {
          "panel": "wb_back",
          "edge": 0
        }
      ],
      [
        {
          "panel": "wb_front",
          "edge": 1
        },
        {
          "panel": "wb_back",
          "edge": 3
        }
      ],
      [
        {
          "panel": "right_ftorso",
          "edge": 6
        },
        {
          "panel": "wb_front",
          "edge": 3
        }
      ],
      [
        {
          "panel": "left_ftorso",
          "edge": 0
        },
        {
          "panel": "wb_front",
          "edge": 2
        }
      ],
      [
        {
          "panel": "left_btorso",
          "edge": 5
        },
        {
          "panel": "wb_back",
          "edge": 2
        }
      ],
      [
        {
          "panel": "right_btorso",
          "edge": 0
        },
        {
          "panel": "wb_back",
          "edge": 1
        }
      ]
    ],
    "panel_order": [
      "sl_right_cuff_b",
      "sl_right_cuff_skirt_b",
      "sl_right_cuff_f",
      "sl_right_cuff_skirt_f",
      "right_sleeve_b",
      "right_sleeve_f",
      "right_btorso",
      "right_ftorso",
      "right_collar_back",
      "right_collar_front",
      "wb_back",
      "wb_front",
      "left_collar_front",
      "left_btorso",
      "left_ftorso",
      "left_collar_back",
      "left_sleeve_b",
      "left_sleeve_f",
      "sl_left_cuff_b",
      "sl_left_cuff_skirt_b",
      "sl_left_cuff_f",
      "sl_left_cuff_skirt_f"
    ]
  },
  "parameters": {},
  "parameter_order": [],
  "properties": {
    "curvature_coords": "relative",
    "normalize_panel_translation": false,
    "normalized_edge_loops": true,
    "units_in_meter": 100
  }
}