{
  "pattern": {
    "panels": {
      "wb_back": {
        "translation": [
          -28.023859721726446,
          81.72585292084176,
          -15.0
        ],
        "rotation": [
          0.0,
          0.0,
          0.0
        ],
        "vertices": [
          [
            0,
            0
          ],
          [
            0,
            4.69674
          ],
          [
            28.023859721726446,
            4.69674
          ],
          [
            56.04771944345289,
            4.69674
          ],
          [
            56.04771944345289,
            0
          ]
        ],
        "edges": [
          {
            "endpoints": [
              0,
              1
            ]
          },
          {
            "endpoints": [
              1,
              2
            ],
            "label": "lower_interface"
          },
          {
            "endpoints": [
              2,
              3
            ],
            "label": "lower_interface"
          },
          {
            "endpoints": [
              3,
              4
            ]
          },
          {
            "endpoints": [
              4,
              0
            ]
          }
        ],
        "label": "body"
      },
      "wb_front": {
        "translation": [
          -32.36480183623669,
          81.72585292084176,
          20.0
        ],
        "rotation": [
          0.0,
          0.0,
          0.0
        ],
        "vertices": [
          [
            0,
            0
          ],
          [
            64.72960367247337,
            0
          ],
          [
            64.72960367247337,
            4.69674
          ],
          [
            32.36480183623669,
            4.69674
          ],
          [
            0,
            4.69674
          ]
        ],
        "edges": [
          {
            "endpoints": [
              0,
              1
            ]
          },
          {
            "endpoints": [
              1,
              2
            ]
          },
          {
            "endpoints": [
              2,
              3
            ],
            "label": "lower_interface"
          },
          {
            "endpoints": [
              3,
              4
            ],
            "label": "lower_interface"
          },
          {
            "endpoints": [
              4,
              0
            ]
          }
        ],
        "label": "body"
      },
      "left_btorso": {
        "translation": [
          0.0,
          91.4448950181744,
          -25.0
        ],
        "rotation": [
          0.0,
          0.0,
          0.0
        ],
        "vertices": [
          [
            0.0,
            0.0
          ],
          [
            0.0,
            44.26955999493607
          ],
          [
            10.205373684241769,
            44.26955999493607
          ],
          [
            11.722199256487272,
            49.559359404372294
          ],
          [
            16.06358123424115,
            47.833670201658734
          ],
          [
            29.892158926214535,
            29.392190201658735
          ],
          [
            39.49808376482134,
            0.0
          ]
        ],
        "edges": [
          {
            "endpoints": [
              0,
              1
            ]
          },
          {
            "endpoints": [
              1,
              2
            ],
            "label": "left_collar"
          },
          {
            "endpoints": [
              2,
              3
            ],
            "label": "left_collar"
          },
          {
            "endpoints": [
              3,
              4
            ]
          },
          {
            "endpoints": [
              4,
              5
            ],
            "label": "left_armhole",
            "curvature": {
              "type": "cubic",
              "params": [
                [
                  0.5,
                  -0.2
                ],
                [
                  0.8,
                  -0.35
                ]
              ]
            }
          },
          {
            "endpoints": [
              5,
              6
            ]
          },
          {
            "endpoints": [
              6,
              0
            ]
          }
        ],
        "label": "body"
      },
      "left_sleeve_b": {
        "translation": [
          59.2559668184896,
          105.54675587404745,
          -12.5
        ],
        "rotation": [
          0.0,
          0.0,
          -45.482999999999976
        ],
        "vertices": [
          [
            0.0,
            0.0
          ],
          [
            0.0,
            -22.908152636917343
          ],
          [
            -35.32941696483976,
            -27.614962842718604
          ],
          [
            -51.142669042587215,
            -1.27314406276248
          ],
          [
            -51.27391175995673,
            0.0
          ]
        ],
        "edges": [
          {
            "endpoints": [
              0,
              1
            ]
          },
          {
            "endpoints": [
              1,
              2
            ]
          },
          {
            "endpoints": [
              2,
              3
            ],
            "curvature": {
              "type": "cubic",
              "params": [
                [
                  0.3334114443618361,
                  -0.017205697687595767
                ],
                [
                  0.5986962220512354,
                  0.23483327294257827
                ]
              ]
            }
          },
          {
            "endpoints": [
              3,
              4
            ],
            "curvature": {
              "type": "cubic",
              "params": [
                [
                  0.3415910944108238,
                  0.005829576136658179
                ],
                [
                  0.6748139817251568,
                  0.005751608270382722
                ]
              ]
            }
          },
          {
            "endpoints": [
              4,
              0
            ]
          }
        ],
        "label": "arm"
      },
      "sl_left_cuff_f": {
        "translation": [
          64.44213677972316,
          100.27240223458612,
          17.5
        ],
        "rotation": [
          0.0,
          0.0,
          44.517000000000024
        ],
        "vertices": [
          [
            0.0,
            0.0
          ],
          [
            0.0,
            5.3969700000000005
          ],
          [
            -15.173489679883673,
            5.3969700000000005
          ],
          [
            -15.173489679883673,
            0.0
          ]
        ],
        "edges": [
          {
            "endpoints": [
              0,
              1
            ]
          },
          {
            "endpoints": [
              1,
              2
            ]
          },
          {
            "endpoints": [
              2,
              3
            ]
          },
          {
            "endpoints": [
              3,
              0
            ]
          }
        ],
        "label": "arm"
      },
      "sl_left_cuff_b": {
        "translation": [
          64.44213677972316,
          100.27240223458612,
          -12.5
        ],
        "rotation": [
          0.0,
          0.0,
          44.517000000000024
        ],
        "vertices": [
          [
            0.0,
            0.0
          ],
          [
            -15.173489679883673,
            0.0
          ],
          [
            -15.173489679883673,
            5.3969700000000005
          ],
          [
            0.0,
            5.3969700000000005
          ]
        ],
        "edges": [
          {
            "endpoints": [
              0,
              1
            ]
          },
          {
            "endpoints": [
              1,
              2
            ]
          },
          {
            "endpoints": [
              2,
              3
            ]
          },
          {
            "endpoints": [
              3,
              0
            ]
          }
        ],
        "label": "arm"
      },
      "left_sleeve_f": {
        "translation": [
          59.2559668184896,
          105.54675587404745,
          17.5
        ],
        "rotation": [
          0.0,
          0.0,
          -45.482999999999976
        ],
        "vertices": [
          [
            0.0,
            0.0
          ],
          [
            -51.27391175995674,
            0.0
          ],
          [
            -35.329416964839766,
            -27.614962842718505
          ],
          [
            0.0,
            -22.908152636917258
          ]
        ],
        "edges": [
          {
            "endpoints": [
              0,
              1
            ]
          },
          {
            "endpoints": [
              1,
              2
            ],
            "curvature": {
              "type": "cubic",
              "params": [
                [
                  0.4467131152074817,
                  -0.26028588660334173
                ],
                [
                  0.6558559739596916,
                  0.024801581613630434
                ]
              ]
            }
          },
          {
            "endpoints": [
              2,
              3
            ]
          },
          {
            "endpoints": [
              3,
              0
            ]
          }
        ],
        "label": "arm"
      },
      "left_ftorso": {
        "translation": [
          0.0,
          91.40029082350912,
          30.0
        ],
        "rotation": [
          0.0,
          0.0,
          0.0
        ],
        "vertices": [
          [
            0.0,
            0.0
          ],
          [
            43.21665866877533,
            0.0
          ],
          [
            32.39289207079669,
            29.658903982276765
          ],
          [
            15.878713243657689,
            47.10632593677255
          ],
          [
            15.504814646353438,
            48.10038398227677
          ],
          [
            11.722199256487272,
            49.60396382116295
          ],
          [
            0.0,
            32.207862419884826
          ]
        ],
        "edges": [
          {
            "endpoints": [
              0,
              1
            ]
          },
          {
            "endpoints": [
              1,
              2
            ]
          },
          {
            "endpoints": [
              2,
              3
            ],
            "curvature": {
              "type": "cubic",
              "params": [
                [
                  0.20846203471041747,
                  0.35125152292669926
                ],
                [
                  0.5074232772322997,
                  0.20777663361937315
                ]
              ]
            }
          },
          {
            "endpoints": [
              3,
              4
            ],
            "curvature": {
              "type": "cubic",
              "params": [
                [
                  0.3299197139982398,
                  -0.0003328529572322019
                ],
                [
                  0.6632640465867996,
                  -0.0003997241376189254
                ]
              ]
            }
          },
          {
            "endpoints": [
              4,
              5
            ]
          },
          {
            "endpoints": [
              5,
              6
            ],
            "label": "left_collar",
            "curvature": {
              "type": "quadratic",
              "params": [
                [
                  0.44634552002124805,
                  0.55
                ]
              ]
            }
          },
          {
            "endpoints": [
              6,
              0
            ]
          }
        ],
        "label": "body"
      },
      "right_btorso": {
        "translation": [
          0.0,
          91.4448950181744,
          -25.0
        ],
        "rotation": [
          0.0,
          0.0,
          0.0
        ],
        "vertices": [
          [
            0,
            0
          ],
          [
            -39.49808376482134,
            0
          ],
          [
            -29.892158926214535,
            29.392190201658735
          ],
          [
            -16.06358123424115,
            47.833670201658734
          ],
          [
            -11.722199256487272,
            49.559359404372294
          ],
          [
            -10.205373684241769,
            44.26955999493607
          ],
          [
            0.0,
            44.26955999493607
          ]
        ],
        "edges": [
          {
            "endpoints": [
              0,
              1
            ]
          },
          {
            "endpoints": [
              1,
              2
            ]
          },
          {
            "endpoints": [
              2,
              3
            ],
            "label": "right_armhole",
            "curvature": {
              "type": "cubic",
              "params": [
                [
                  0.19999999999999996,
                  -0.35
                ],
                [
                  0.5,
                  -0.2
                ]
              ]
            }
          },
          {
            "endpoints": [
              3,
              4
            ]
          },
          {
            "endpoints": [
              4,
              5
            ],
            "label": "right_collar"
          },
          {
            "endpoints": [
              5,
              6
            ],
            "label": "right_collar"
          },
          {
            "endpoints": [
              6,
              0
            ]
          }
        ],
        "label": "body"
      },
      "right_ftorso": {
        "translation": [
          0.0,
          91.40029082350912,
          30.0
        ],
        "rotation": [
          0.0,
          0.0,
          0.0
        ],
        "vertices": [
          [
            0,
            0
          ],
          [
            0.0,
            32.207862419884826
          ],
          [
            -11.722199256487272,
            49.60396382116295
          ],
          [
            -15.504814646353438,
            48.10038398227677
          ],
          [
            -15.878713243657689,
            47.10632593677255
          ],
          [
            -32.39289207079669,
            29.658903982276765
          ],
          [
            -43.21665866877533,
            0
          ]
        ],
        "edges": [
          {
            "endpoints": [
              0,
              1
            ]
          },
          {
            "endpoints": [
              1,
              2
            ],
            "label": "right_collar",
            "curvature": {
              "type": "quadratic",
              "params": [
                [
                  0.553654479978752,
                  0.55
                ]
              ]
            }
          },
          {
            "endpoints": [
              2,
              3
            ]
          },
          {
            "endpoints": [
              3,
              4
            ],
            "curvature": {
              "type": "cubic",
              "params": [
                [
                  0.33673595341320045,
                  -0.0003997241376189254
                ],
                [
                  0.6700802860017602,
                  -0.0003328529572322019
                ]
              ]
            }
          },
          {
            "endpoints": [
              4,
              5
            ],
            "curvature": {
              "type": "cubic",
              "params": [
                [
                  0.4925767227677002,
                  0.20777663361937315
                ],
                [
                  0.7915379652895825,
                  0.35125152292669926
                ]
              ]
            }
          },
          {
            "endpoints": [
              5,
              6
            ]
          },
          {
            "endpoints": [
              6,
              0
            ]
          }
        ],
        "label": "body"
      },
      "sl_right_cuff_f": {
        "translation": [
          -64.44213677972316,
          100.27240223458612,
          17.5
        ],
        "rotation": [
          0.0,
          0.0,
          -44.516999999999996
        ],
        "vertices": [
          [
            0,
            0
          ],
          [
            15.173489679883673,
            0
          ],
          [
            15.173489679883673,
            5.3969700000000005
          ],
          [
            0,
            5.3969700000000005
          ]
        ],
        "edges": [
          {
            "endpoints": [
              0,
              1
            ]
          },
          {
            "endpoints": [
              1,
              2
            ]
          },
          {
            "endpoints": [
              2,
              3
            ]
          },
          {
            "endpoints": [
              3,
              0
            ]
          }
        ],
        "label": "arm"
      },
      "sl_right_cuff_b": {
        "translation": [
          -64.44213677972316,
          100.27240223458612,
          -12.5
        ],
        "rotation": [
          0.0,
          0.0,
          -44.516999999999996
        ],
        "vertices": [
          [
            0,
            0
          ],
          [
            0,
            5.3969700000000005
          ],
          [
            15.173489679883673,
            5.3969700000000005
          ],
          [
            15.173489679883673,
            0
          ]
        ],
        "edges": [
          {
            "endpoints": [
              0,
              1
            ]
          },
          {
            "endpoints": [
              1,
              2
            ]
          },
          {
            "endpoints": [
              2,
              3
            ]
          },
          {
            "endpoints": [
              3,
              0
            ]
          }
        ],
        "label": "arm"
      },
      "right_sleeve_f": {
        "translation": [
          -59.2559668184896,
          105.54675587404742,
          17.5
        ],
        "rotation": [
          0.0,
          0.0,
          45.482999999999976
        ],
        "vertices": [
          [
            0,
            0
          ],
          [
            0,
            -22.908152636917258
          ],
          [
            35.329416964839766,
            -27.614962842718505
          ],
          [
            51.27391175995674,
            0.0
          ]
        ],
        "edges": [
          {
            "endpoints": [
              0,
              1
            ]
          },
          {
            "endpoints": [
              1,
              2
            ]
          },
          {
            "endpoints": [
              2,
              3
            ],
            "curvature": {
              "type": "cubic",
              "params": [
                [
                  0.34414402604030836,
                  0.024801581613630434
                ],
                [
                  0.5532868847925183,
                  -0.26028588660334173
                ]
              ]
            }
          },
          {
            "endpoints": [
              3,
              0
            ]
          }
        ],
        "label": "arm"
      },
      "right_sleeve_b": {
        "translation": [
          -59.2559668184896,
          105.54675587404742,
          -12.5
        ],
        "rotation": [
          0.0,
          0.0,
          45.482999999999976
        ],
        "vertices": [
          [
            0,
            0
          ],
          [
            51.27391175995673,
            0.0
          ],
          [
            51.142669042587215,
            -1.27314406276248
          ],
          [
            35.32941696483976,
            -27.614962842718604
          ],
          [
            0,
            -22.908152636917343
          ]
        ],
        "edges": [
          {
            "endpoints": [
              0,
              1
            ]
          },
          {
            "endpoints": [
              1,
              2
            ],
            "curvature": {
              "type": "cubic",
              "params": [
                [
                  0.32518601827484317,
                  0.005751608270382722
                ],
                [
                  0.6584089055891762,
                  0.005829576136658179
                ]
              ]
            }
          },
          {
            "endpoints": [
              2,
              3
            ],
            "curvature": {
              "type": "cubic",
              "params": [
                [
                  0.4013037779487646,
                  0.23483327294257827
                ],
                [
                  0.6665885556381639,
                  -0.017205697687595767
                ]
              ]
            }
          },
          {
            "endpoints": [
              3,
              4
            ]
          },
          {
            "endpoints": [
              4,
              0
            ]
          }
        ],
        "label": "arm"
      }
    },
    "stitches": [
      [
        {
          "panel": "wb_front",
          "edge": 4
        },
        {
          "panel": "wb_back",
          "edge": 0
        }
      ],
      [
        {
          "panel": "wb_front",
          "edge": 1
        },
        {
          "panel": "wb_back",
          "edge": 3
        }
      ],
      [
        {
          "panel": "sl_left_cuff_f",
          "edge": 0
        },
        {
          "panel": "sl_left_cuff_b",
          "edge": 3
        }
      ],
      [
        {
          "panel": "sl_left_cuff_f",
          "edge": 2
        },
        {
          "panel": "sl_left_cuff_b",
          "edge": 1
        }
      ],
      [
        {
          "panel": "left_sleeve_f",
          "edge": 0
        },
        {
          "panel": "left_sleeve_b",
          "edge": 4
        }
      ],
      [
        {
          "panel": "left_sleeve_f",
          "edge": 2
        },
        {
          "panel": "left_sleeve_b",
          "edge": 1
        }
      ],
      [
        {
          "panel": "sl_left_cuff_f",
          "edge": 1
        },
        {
          "panel": "left_sleeve_f",
          "edge": 3
        }
      ],
      [
        {
          "panel": "sl_left_cuff_b",
          "edge": 2
        },
        {
          "panel": "left_sleeve_b",
          "edge": 0
        }
      ],
      [
        {
          "panel": "left_sleeve_f",
          "edge": 1
        },
        {
          "panel": "left_ftorso",
          "edge": 2
        }
      ],
      [
        {
          "panel": "left_sleeve_b",
          "edge": 3
        },
        {
          "panel": "left_ftorso",
          "edge": 3
        }
      ],
      [
        {
          "panel": "left_sleeve_b",
          "edge": 2
        },
        {
          "panel": "left_btorso",
          "edge": 4
        }
      ],
      [
        {
          "panel": "left_ftorso",
          "edge": 4
        },
        {
          "panel": "left_btorso",
          "edge": 3
        }
      ],
      [
        {
          "panel": "left_ftorso",
          "edge": 1
        },
        {
          "panel": "left_btorso",
          "edge": 5
        }
      ],
      [
        {
          "panel": "sl_right_cuff_f",
          "edge": 3
        },
        {
          "panel": "sl_right_cuff_b",
          "edge": 0
        }
      ],
      [
        {
          "panel": "sl_right_cuff_f",
          "edge": 1
        },
        {
          "panel": "sl_right_cuff_b",
          "edge": 2
        }
      ],
      [
        {
          "panel": "right_sleeve_f",
          "edge": 3
        },
        {
          "panel": "right_sleeve_b",
          "edge": 0
        }
      ],
      [
        {
          "panel": "right_sleeve_f",
          "edge": 1
        },
        {
          "panel": "right_sleeve_b",
          "edge": 3
        }
      ],
      [
        {
          "panel": "sl_right_cuff_f",
          "edge": 2
        },
        {
          "panel": "right_sleeve_f",
          "edge": 0
        }
      ],
      [
        {
          "panel": "sl_right_cuff_b",
          "edge": 1
        },
        {
          "panel": "right_sleeve_b",
          "edge": 4
        }
      ],
      [
        {
          "panel": "right_sleeve_f",
          "edge": 2
        },
        {
          "panel": "right_ftorso",
          "edge": 4
        }
      ],
      [
        {
          "panel": "right_sleeve_b",
          "edge": 1
        },
        {
          "panel": "right_ftorso",
          "edge": 3
        }
      ],
      [
        {
          "panel": "right_sleeve_b",
          "edge": 2
        },
        {
          "panel": "right_btorso",
          "edge": 2
        }
      ],
      [
        {
          "panel": "right_ftorso",
          "edge": 2
        },
        {
          "panel": "right_btorso",
          "edge": 3
        }
      ],
      [
        {
          "panel": "right_ftorso",
          "edge": 5
        },
        {
          "panel": "right_btorso",
          "edge": 1
        }
      ],
      [
        {
          "panel": "right_ftorso",
          "edge": 0
        },
        {
          "panel": "left_ftorso",
          "edge": 6
        }
      ],
      [
        {
          "panel": "right_btorso",
          "edge": 6
        },
        {
          "panel": "left_btorso",
          "edge": 0
        }
      ],
      [
        {
          "panel": "right_ftorso",
          "edge": 6
        },
        {
          "panel": "wb_front",
          "edge": 3
        }
      ],
      [
        {
          "panel": "left_ftorso",
          "edge": 0
        },
        {
          "panel": "wb_front",
          "edge": 2
        }
      ],
      [
        {
          "panel": "left_btorso",
          "edge": 6
        },
        {
          "panel": "wb_back",
          "edge": 2
        }
      ],
      [
        {
          "panel": "right_btorso",
          "edge": 0
        },
        {
          "panel": "wb_back",
          "edge": 1
        }
      ]
    ],
    "panel_order": [
      "sl_right_cuff_b",
      "sl_right_cuff_f",
      "right_sleeve_b",
      "right_sleeve_f",
      "right_btorso",
      "right_ftorso",
      "wb_back",
      "wb_front",
      "left_btorso",
      "left_ftorso",
      "left_sleeve_b",
      "left_sleeve_f",
      "sl_left_cuff_b",
      "sl_left_cuff_f"
    ]
  },
  "parameters": {},
  "parameter_order": [],
  "properties": {
    "curvature_coords": "relative",
    "normalize_panel_translation": false,
    "normalized_edge_loops": true,
    "units_in_meter": 100
  }
}