{
  "pattern": {
    "panels": {
      "left_collar_front": {
        "translation": [
          8.0,
          153.6638,
          35.0
        ],
        "rotation": [
          0.0,
          0.0,
          0.0
        ],
        "vertices": [
          [
            0.0,
            0.0
          ],
          [
            -4.0,
            0.0
          ],
          [
            -4.0,
            -38.96029723142812
          ]
        ],
        "edges": [
          {
            "endpoints": [
              0,
              1
            ]
          },
          {
            "endpoints": [
              1,
              2
            ]
          },
          {
            "endpoints": [
              2,
              0
            ],
            "curvature": {
              "type": "quadratic",
              "params": [
                [
                  0.7,
                  -0.2
                ]
              ]
            }
          }
        ],
        "label": "body"
      },
      "left_collar_back": {
        "translation": [
          16.830311087551745,
          149.6638,
          -10.0
        ],
        "rotation": [
          0.0,
          0.0,
          0.0
        ],
        "vertices": [
          [
            0.0,
            0.0
          ],
          [
            -16.830311087551745,
            0.0
          ],
          [
            -16.830311087551745,
            4.0
          ],
          [
            0.0,
            4.0
          ]
        ],
        "edges": [
          {
            "endpoints": [
              0,
              1
            ]
          },
          {
            "endpoints": [
              1,
              2
            ]
          },
          {
            "endpoints": [
              2,
              3
            ]
          },
          {
            "endpoints": [
              3,
              0
            ]
          }
        ],
        "label": "body"
      },
      "left_btorso": {
        "translation": [
          0.0,
          89.94462233165838,
          -25.0
        ],
        "rotation": [
          0.0,
          0.0,
          0.0
        ],
        "vertices": [
          [
            0.0,
            0.0
          ],
          [
            0.0,
            40.76447012973973
          ],
          [
            10.81880000000001,
            51.41873119485778
          ],
          [
            17.68083671719851,
            48.69108796340856
          ],
          [
            17.68083671719851,
            26.95776733188371
          ],
          [
            27.032802271037546,
            26.95776733188371
          ],
          [
            24.27432514376948,
            0.0
          ]
        ],
        "edges": [
          {
            "endpoints": [
              0,
              1
            ]
          },
          {
            "endpoints": [
              1,
              2
            ],
            "label": "left_collar",
            "curvature": {
              "type": "circle",
              "params": [
                10.820070527394034,
                0,
                1
              ]
            }
          },
          {
            "endpoints": [
              2,
              3
            ]
          },
          {
            "endpoints": [
              3,
              4
            ],
            "label": "left_armhole"
          },
          {
            "endpoints": [
              4,
              5
            ],
            "label": "left_armhole"
          },
          {
            "endpoints": [
              5,
              6
            ]
          },
          {
            "endpoints": [
              6,
              0
            ]
          }
        ],
        "label": "body"
      },
      "left_ftorso": {
        "translation": [
          0.0,
          89.75877390868105,
          30.0
        ],
        "rotation": [
          0.0,
          0.0,
          0.0
        ],
        "vertices": [
          [
            0.0,
            0.0
          ],
          [
            26.559648574331323,
            0.0
          ],
          [
            29.653486627914653,
            27.0767181673409
          ],
          [
            17.84913509358274,
            27.0767181673409
          ],
          [
            17.84913509358274,
            48.81003879886576
          ],
          [
            10.8188,
            51.6045794350691
          ],
          [
            0.0,
            14.176537448862746
          ]
        ],
        "edges": [
          {
            "endpoints": [
              0,
              1
            ]
          },
          {
            "endpoints": [
              1,
              2
            ]
          },
          {
            "endpoints": [
              2,
              3
            ],
            "label": "left_armhole"
          },
          {
            "endpoints": [
              3,
              4
            ],
            "label": "left_armhole"
          },
          {
            "endpoints": [
              4,
              5
            ]
          },
          {
            "endpoints": [
              5,
              6
            ],
            "label": "left_collar"
          },
          {
            "endpoints": [
              6,
              0
            ]
          }
        ],
        "label": "body"
      },
      "right_btorso": {
        "translation": [
          0.0,
          89.94462233165838,
          -25.0
        ],
        "rotation": [
          0.0,
          0.0,
          0.0
        ],
        "vertices": [
          [
            0,
            0
          ],
          [
            -24.27432514376948,
            0
          ],
          [
            -27.032802271037546,
            26.95776733188371
          ],
          [
            -17.68083671719851,
            26.95776733188371
          ],
          [
            -17.68083671719851,
            48.69108796340856
          ],
          [
            -10.81880000000001,
            51.41873119485778
          ],
          [
            0.0,
            40.76447012973973
          ]
        ],
        "edges": [
          {
            "endpoints": [
              0,
              1
            ]
          },
          {
            "endpoints": [
              1,
              2
            ]
          },
          {
            "endpoints": [
              2,
              3
            ],
            "label": "right_armhole"
          },
          {
            "endpoints": [
              3,
              4
            ],
            "label": "right_armhole"
          },
          {
            "endpoints": [
              4,
              5
            ]
          },
          {
            "endpoints": [
              5,
              6
            ],
            "label": "right_collar",
            "curvature": {
              "type": "circle",
              "params": [
                10.820070527394034,
                0,
                1
              ]
            }
          },
          {
            "endpoints": [
              6,
              0
            ]
          }
        ],
        "label": "body"
      },
      "right_collar_front": {
        "translation": [
          -8.0,
          153.6638,
          35.0
        ],
        "rotation": [
          0.0,
          0.0,
          0.0
        ],
        "vertices": [
          [
            0,
            0
          ],
          [
            4,
            -38.96029723142812
          ],
          [
            4,
            0
          ]
        ],
        "edges": [
          {
            "endpoints": [
              0,
              1
            ],
            "curvature": {
              "type": "quadratic",
              "params": [
                [
                  0.30000000000000004,
                  -0.2
                ]
              ]
            }
          },
          {
            "endpoints": [
              1,
              2
            ]
          },
          {
            "endpoints": [
              2,
              0
            ]
          }
        ],
        "label": "body"
      },
      "right_collar_back": {
        "translation": [
          -16.830311087551745,
          149.6638,
          -10.0
        ],
        "rotation": [
          0.0,
          0.0,
          0.0
        ],
        "vertices": [
          [
            0,
            0
          ],
          [
            0,
            4
          ],
          [
            16.830311087551745,
            4
          ],
          [
            16.830311087551745,
            0
          ]
        ],
        "edges": [
          {
            "endpoints": [
              0,
              1
            ]
          },
          {
            "endpoints": [
              1,
              2
            ]
          },
          {
            "endpoints": [
              2,
              3
            ]
          },
          {
            "endpoints": [
              3,
              0
            ]
          }
        ],
        "label": "body"
      },
      "right_ftorso": {
        "translation": [
          0.0,
          89.75877390868105,
          30.0
        ],
        "rotation": [
          0.0,
          0.0,
          0.0
        ],
        "vertices": [
          [
            0,
            0
          ],
          [
            0.0,
            14.176537448862746
          ],
          [
            -10.8188,
            51.6045794350691
          ],
          [
            -17.84913509358274,
            48.81003879886576
          ],
          [
            -17.84913509358274,
            27.0767181673409
          ],
          [
            -29.653486627914653,
            27.0767181673409
          ],
          [
            -26.559648574331323,
            0
          ]
        ],
        "edges": [
          {
            "endpoints": [
              0,
              1
            ]
          },
          {
            "endpoints": [
              1,
              2
            ],
            "label": "right_collar"
          },
          {
            "endpoints": [
              2,
              3
            ]
          },
          {
            "endpoints": [
              3,
              4
            ],
            "label": "right_armhole"
          },
          {
            "endpoints": [
              4,
              5
            ],
            "label": "right_armhole"
          },
          {
            "endpoints": [
              5,
              6
            ]
          },
          {
            "endpoints": [
              6,
              0
            ]
          }
        ],
        "label": "body"
      }
    },
    "stitches": [
      [
        {
          "panel": "left_collar_front",
          "edge": 0
        },
        {
          "panel": "left_collar_back",
          "edge": 3
        },
        "right_wrong"
      ],
      [
        {
          "panel": "left_ftorso",
          "edge": 5
        },
        {
          "panel": "left_collar_front",
          "edge": 1
        },
        "right_wrong"
      ],
      [
        {
          "panel": "left_btorso",
          "edge": 1
        },
        {
          "panel": "left_collar_back",
          "edge": 0
        }
      ],
      [
        {
          "panel": "left_ftorso",
          "edge": 4
        },
        {
          "panel": "left_btorso",
          "edge": 2
        }
      ],
      [
        {
          "panel": "left_ftorso",
          "edge": 1
        },
        {
          "panel": "left_btorso",
          "edge": 5
        }
      ],
      [
        {
          "panel": "right_collar_front",
          "edge": 2
        },
        {
          "panel": "right_collar_back",
          "edge": 0
        },
        "right_wrong"
      ],
      [
        {
          "panel": "right_ftorso",
          "edge": 1
        },
        {
          "panel": "right_collar_front",
          "edge": 1
        },
        "right_wrong"
      ],
      [
        {
          "panel": "right_btorso",
          "edge": 5
        },
        {
          "panel": "right_collar_back",
          "edge": 3
        }
      ],
      [
        {
          "panel": "right_ftorso",
          "edge": 2
        },
        {
          "panel": "right_btorso",
          "edge": 4
        }
      ],
      [
        {
          "panel": "right_ftorso",
          "edge": 5
        },
        {
          "panel": "right_btorso",
          "edge": 1
        }
      ],
      [
        {
          "panel": "right_ftorso",
          "edge": 0
        },
        {
          "panel": "left_ftorso",
          "edge": 6
        }
      ],
      [
        {
          "panel": "right_btorso",
          "edge": 6
        },
        {
          "panel": "left_btorso",
          "edge": 0
        }
      ],
      [
        {
          "panel": "right_collar_back",
          "edge": 2
        },
        {
          "panel": "left_collar_back",
          "edge": 1
        }
      ]
    ],
    "panel_order": [
      "right_btorso",
      "right_ftorso",
      "right_collar_back",
      "right_collar_front",
      "left_btorso",
      "left_ftorso",
      "left_collar_back",
      "left_collar_front"
    ]
  },
  "parameters": {},
  "parameter_order": [],
  "properties": {
    "curvature_coords": "relative",
    "normalize_panel_translation": false,
    "normalized_edge_loops": true,
    "units_in_meter": 100
  }
}